best_testrail_client/__init__.py
best_testrail_client/client.py
best_testrail_client/custom_types.py
best_testrail_client/enums.py
best_testrail_client/exceptions.py
best_testrail_client/utils.py
best_testrail_client/api/__init__.py
best_testrail_client/api/attachments_api.py
best_testrail_client/api/base_api.py
best_testrail_client/api/case_types_api.py
best_testrail_client/api/cases_api.py
best_testrail_client/api/configurations_api.py
best_testrail_client/api/milestoness_api.py
best_testrail_client/api/priorities_api.py
best_testrail_client/api/result_fields_api.py
best_testrail_client/api/results_api.py
best_testrail_client/api/runs_api.py
best_testrail_client/api/sections_api.py
best_testrail_client/api/statuses_api.py
best_testrail_client/api/templates_api.py
best_testrail_client/api/tests_api.py
best_testrail_client/api/users_api.py
best_testrail_client/models/__init__.py
best_testrail_client/models/attachment.py
best_testrail_client/models/basemodel.py
best_testrail_client/models/case.py
best_testrail_client/models/case_type.py
best_testrail_client/models/configuration.py
best_testrail_client/models/milestone.py
best_testrail_client/models/priority.py
best_testrail_client/models/result.py
best_testrail_client/models/result_field.py
best_testrail_client/models/run.py
best_testrail_client/models/section.py
best_testrail_client/models/status.py
best_testrail_client/models/template.py
best_testrail_client/models/test.py
best_testrail_client/models/user.py
tests/__init__.py
tests/conftest.py
tests/test_utils.py
tests/test_api/__init__.py
tests/test_api/conftest.py
tests/test_api/test_attachments.py
tests/test_api/test_case_types.py
tests/test_api/test_cases_api.py
tests/test_api/test_configurations.py
tests/test_api/test_milestones.py
tests/test_api/test_priorities.py
tests/test_api/test_result_fields.py
tests/test_api/test_results.py
tests/test_api/test_runs.py
tests/test_api/test_sections.py
tests/test_api/test_statuses.py
tests/test_api/test_templates.py
best_testrail_client-0.0.2.dist-info/LICENSE
best_testrail_client-0.0.2.dist-info/METADATA
best_testrail_client-0.0.2.dist-info/WHEEL
best_testrail_client-0.0.2.dist-info/top_level.txt
best_testrail_client-0.0.2.dist-info/RECORD
