Metadata-Version: 2.1
Name: best-testrail-client
Version: 0.0.2
Summary: TestRail client implementing all API v2.
Home-page: https://github.com/best-doctor/best_testrail_client
Author: Valery Pavlov
Author-email: lerikpav@gmail.com
License: MIT
Keywords: testrail test report
Platform: UNKNOWN
Classifier: Development Status :: 3 - Alpha
Classifier: Environment :: Console
Classifier: Operating System :: OS Independent
Classifier: Topic :: Software Development :: Libraries :: Python Modules
Classifier: Programming Language :: Python
Classifier: Programming Language :: Python :: 3.7
Classifier: Programming Language :: Python :: 3.8
Requires-Dist: setuptools
Requires-Dist: requests (>=2.22.0)
Requires-Dist: typing-extensions (>=3.7.2)
